[{"score":2611111,"world_rank":22,"area_rank":11,"realm_rank":1,"name":"Draama","url":"http:\/\/www.wowprogress.com\/guild\/eu\/chromaggus\/Draama\/rating.tier12_25"},{"score":606667,"world_rank":1084,"area_rank":575,"realm_rank":2,"name":"Sacred Rite","url":"http:\/\/www.wowprogress.com\/guild\/eu\/chromaggus\/Sacred+Rite\/rating.tier12_25"},{"score":489445,"world_rank":1920,"area_rank":1062,"realm_rank":3,"name":"Furia","url":"http:\/\/www.wowprogress.com\/guild\/eu\/chromaggus\/Furia\/rating.tier12_25"},{"score":213056,"world_rank":2758,"area_rank":1529,"realm_rank":4,"name":"Oracle","url":"http:\/\/www.wowprogress.com\/guild\/eu\/chromaggus\/Oracle\/rating.tier12_25"},{"score":125277,"world_rank":3279,"area_rank":1785,"realm_rank":5,"name":"Haunted Heavens","url":"http:\/\/www.wowprogress.com\/guild\/eu\/chromaggus\/Haunted+Heavens\/rating.tier12_25"},{"score":112778,"world_rank":3384,"area_rank":1837,"realm_rank":6,"name":"FIN","url":"http:\/\/www.wowprogress.com\/guild\/eu\/chromaggus\/FIN\/rating.tier12_25"},{"score":13000,"world_rank":4760,"area_rank":2555,"realm_rank":7,"name":"Prozac Hunters","url":"http:\/\/www.wowprogress.com\/guild\/eu\/chromaggus\/Prozac+Hunters\/rating.tier12_25"},{"score":10978,"world_rank":4988,"area_rank":2693,"realm_rank":8,"name":"Never Easy","url":"http:\/\/www.wowprogress.com\/guild\/eu\/chromaggus\/Never+Easy\/rating.tier12_25"},{"score":3528,"world_rank":5761,"area_rank":3113,"realm_rank":9,"name":"Blood and Sand","url":"http:\/\/www.wowprogress.com\/guild\/eu\/chromaggus\/Blood+and+Sand\/rating.tier12_25"},{"score":1378,"world_rank":6281,"area_rank":3392,"realm_rank":10,"name":"Stara Gwardia","url":"http:\/\/www.wowprogress.com\/guild\/eu\/chromaggus\/Stara+Gwardia\/rating.tier12_25"}]