[{"score":2242860,"world_rank":105,"area_rank":61,"realm_rank":1,"name":"E V O","url":"http:\/\/www.wowprogress.com\/guild\/eu\/shattered-hand\/E+V+O\/rating.tier10_25"},{"score":1689601,"world_rank":505,"area_rank":252,"realm_rank":2,"name":"Order Of The Hammer","url":"http:\/\/www.wowprogress.com\/guild\/eu\/shattered-hand\/Order+Of+The+Hammer\/rating.tier10_25"},{"score":698879,"world_rank":1130,"area_rank":637,"realm_rank":3,"name":"Hindsight","url":"http:\/\/www.wowprogress.com\/guild\/eu\/shattered-hand\/Hindsight\/rating.tier10_25"},{"score":601630,"world_rank":2137,"area_rank":1136,"realm_rank":4,"name":"evo stars","url":"http:\/\/www.wowprogress.com\/guild\/eu\/shattered-hand\/evo+stars\/rating.tier10_25"},{"score":572826,"world_rank":2534,"area_rank":1323,"realm_rank":5,"name":"Exercitum","url":"http:\/\/www.wowprogress.com\/guild\/eu\/shattered-hand\/Exercitum\/rating.tier10_25"},{"score":557064,"world_rank":2756,"area_rank":1430,"realm_rank":6,"name":"Last Generation","url":"http:\/\/www.wowprogress.com\/guild\/eu\/shattered-hand\/Last+Generation\/rating.tier10_25"},{"score":515220,"world_rank":3387,"area_rank":1726,"realm_rank":7,"name":"Everlasted","url":"http:\/\/www.wowprogress.com\/guild\/eu\/shattered-hand\/Everlasted\/rating.tier10_25"},{"score":499791,"world_rank":3591,"area_rank":1819,"realm_rank":8,"name":"Vindictive","url":"http:\/\/www.wowprogress.com\/guild\/eu\/shattered-hand\/Vindictive\/rating.tier10_25"},{"score":499351,"world_rank":3599,"area_rank":1822,"realm_rank":9,"name":"Victus","url":"http:\/\/www.wowprogress.com\/guild\/eu\/shattered-hand\/Victus\/rating.tier10_25"},{"score":486572,"world_rank":3779,"area_rank":1909,"realm_rank":10,"name":"Rebound","url":"http:\/\/www.wowprogress.com\/guild\/eu\/shattered-hand\/Rebound\/rating.tier10_25"},{"score":439333,"world_rank":4387,"area_rank":2231,"realm_rank":11,"name":"Evokian","url":"http:\/\/www.wowprogress.com\/guild\/eu\/shattered-hand\/Evokian\/rating.tier10_25"},{"score":404385,"world_rank":4757,"area_rank":2447,"realm_rank":12,"name":"Skill Capped","url":"http:\/\/www.wowprogress.com\/guild\/eu\/shattered-hand\/Skill+Capped\/rating.tier10_25"},{"score":374618,"world_rank":5059,"area_rank":2627,"realm_rank":13,"name":"Carrion","url":"http:\/\/www.wowprogress.com\/guild\/eu\/shattered-hand\/Carrion\/rating.tier10_25"},{"score":361554,"world_rank":5198,"area_rank":2702,"realm_rank":14,"name":"Ghost Division","url":"http:\/\/www.wowprogress.com\/guild\/eu\/shattered-hand\/Ghost+Division\/rating.tier10_25"},{"score":360811,"world_rank":5205,"area_rank":2706,"realm_rank":15,"name":"D A W N","url":"http:\/\/www.wowprogress.com\/guild\/eu\/shattered-hand\/D+A+W+N\/rating.tier10_25"},{"score":326176,"world_rank":5510,"area_rank":2894,"realm_rank":16,"name":"Paradise Lost","url":"http:\/\/www.wowprogress.com\/guild\/eu\/shattered-hand\/Paradise+Lost\/rating.tier10_25"},{"score":300662,"world_rank":5713,"area_rank":3015,"realm_rank":17,"name":"Vicious","url":"http:\/\/www.wowprogress.com\/guild\/eu\/shattered-hand\/Vicious\/rating.tier10_25"},{"score":284177,"world_rank":5834,"area_rank":3088,"realm_rank":18,"name":"Reptilia","url":"http:\/\/www.wowprogress.com\/guild\/eu\/shattered-hand\/Reptilia\/rating.tier10_25"},{"score":245370,"world_rank":6163,"area_rank":3292,"realm_rank":19,"name":"L F M","url":"http:\/\/www.wowprogress.com\/guild\/eu\/shattered-hand\/L+F+M\/rating.tier10_25"},{"score":232929,"world_rank":6317,"area_rank":3372,"realm_rank":20,"name":"Kalmankaarti","url":"http:\/\/www.wowprogress.com\/guild\/eu\/shattered-hand\/Kalmankaarti\/rating.tier10_25"},{"score":229845,"world_rank":6367,"area_rank":3395,"realm_rank":21,"name":"Daemonicus","url":"http:\/\/www.wowprogress.com\/guild\/eu\/shattered-hand\/Daemonicus\/rating.tier10_25"},{"score":185566,"world_rank":7144,"area_rank":3737,"realm_rank":22,"name":"C Star","url":"http:\/\/www.wowprogress.com\/guild\/eu\/shattered-hand\/C+Star\/rating.tier10_25"},{"score":169412,"world_rank":7570,"area_rank":3966,"realm_rank":23,"name":"Drunken Monkeys","url":"http:\/\/www.wowprogress.com\/guild\/eu\/shattered-hand\/Drunken+Monkeys\/rating.tier10_25"},{"score":168822,"world_rank":7590,"area_rank":3973,"realm_rank":24,"name":"CN Force","url":"http:\/\/www.wowprogress.com\/guild\/eu\/shattered-hand\/CN+Force\/rating.tier10_25"},{"score":167856,"world_rank":7609,"area_rank":3983,"realm_rank":25,"name":"Apact","url":"http:\/\/www.wowprogress.com\/guild\/eu\/shattered-hand\/Apact\/rating.tier10_25"},{"score":161111,"world_rank":7776,"area_rank":4055,"realm_rank":26,"name":"Loco Motives","url":"http:\/\/www.wowprogress.com\/guild\/eu\/shattered-hand\/Loco+Motives\/rating.tier10_25"},{"score":134934,"world_rank":8534,"area_rank":4398,"realm_rank":27,"name":"Contra Mund\u00fam","url":"http:\/\/www.wowprogress.com\/guild\/eu\/shattered-hand\/Contra+Mund%C3%BAm\/rating.tier10_25"},{"score":133426,"world_rank":8578,"area_rank":4424,"realm_rank":28,"name":"HoaX","url":"http:\/\/www.wowprogress.com\/guild\/eu\/shattered-hand\/HoaX\/rating.tier10_25"},{"score":128043,"world_rank":8740,"area_rank":4505,"realm_rank":29,"name":"LiVE","url":"http:\/\/www.wowprogress.com\/guild\/eu\/shattered-hand\/LiVE\/rating.tier10_25"},{"score":84700,"world_rank":9912,"area_rank":5114,"realm_rank":30,"name":"W A N T E D","url":"http:\/\/www.wowprogress.com\/guild\/eu\/shattered-hand\/W+A+N+T+E+D\/rating.tier10_25"},{"score":82149,"world_rank":9979,"area_rank":5152,"realm_rank":31,"name":"RELAX BRO WE GOT THIS","url":"http:\/\/www.wowprogress.com\/guild\/eu\/shattered-hand\/RELAX+BRO+WE+GOT+THIS\/rating.tier10_25"},{"score":56896,"world_rank":10556,"area_rank":5446,"realm_rank":32,"name":"Blind Faith","url":"http:\/\/www.wowprogress.com\/guild\/eu\/shattered-hand\/Blind+Faith\/rating.tier10_25"},{"score":24771,"world_rank":11423,"area_rank":5955,"realm_rank":33,"name":"Swiftness","url":"http:\/\/www.wowprogress.com\/guild\/eu\/shattered-hand\/Swiftness\/rating.tier10_25"},{"score":20089,"world_rank":11789,"area_rank":6116,"realm_rank":34,"name":"The Legion","url":"http:\/\/www.wowprogress.com\/guild\/eu\/shattered-hand\/The+Legion\/rating.tier10_25"},{"score":10593,"world_rank":13080,"area_rank":6798,"realm_rank":35,"name":"NatWest","url":"http:\/\/www.wowprogress.com\/guild\/eu\/shattered-hand\/NatWest\/rating.tier10_25"},{"score":8723,"world_rank":13493,"area_rank":7013,"realm_rank":36,"name":"Theorycraft","url":"http:\/\/www.wowprogress.com\/guild\/eu\/shattered-hand\/Theorycraft\/rating.tier10_25"},{"score":8519,"world_rank":13529,"area_rank":7037,"realm_rank":37,"name":"Team Hannibal","url":"http:\/\/www.wowprogress.com\/guild\/eu\/shattered-hand\/Team+Hannibal\/rating.tier10_25"},{"score":8259,"world_rank":13647,"area_rank":7095,"realm_rank":38,"name":"Valhalla","url":"http:\/\/www.wowprogress.com\/guild\/eu\/shattered-hand\/Valhalla\/rating.tier10_25"},{"score":7027,"world_rank":14367,"area_rank":7523,"realm_rank":39,"name":"Havoc","url":"http:\/\/www.wowprogress.com\/guild\/eu\/shattered-hand\/Havoc\/rating.tier10_25"},{"score":6963,"world_rank":14426,"area_rank":7557,"realm_rank":40,"name":"Evil Industries","url":"http:\/\/www.wowprogress.com\/guild\/eu\/shattered-hand\/Evil+Industries\/rating.tier10_25"},{"score":6444,"world_rank":14880,"area_rank":7830,"realm_rank":41,"name":"Razvoj","url":"http:\/\/www.wowprogress.com\/guild\/eu\/shattered-hand\/Razvoj\/rating.tier10_25"},{"score":6444,"world_rank":14901,"area_rank":7846,"realm_rank":42,"name":"Postmortem","url":"http:\/\/www.wowprogress.com\/guild\/eu\/shattered-hand\/Postmortem\/rating.tier10_25"},{"score":5934,"world_rank":15245,"area_rank":8034,"realm_rank":43,"name":"Cataclysm","url":"http:\/\/www.wowprogress.com\/guild\/eu\/shattered-hand\/Cataclysm\/rating.tier10_25"},{"score":5361,"world_rank":15780,"area_rank":8345,"realm_rank":44,"name":"Feel Good Inc","url":"http:\/\/www.wowprogress.com\/guild\/eu\/shattered-hand\/Feel+Good+Inc\/rating.tier10_25"},{"score":5086,"world_rank":16095,"area_rank":8514,"realm_rank":45,"name":"Cake or Death","url":"http:\/\/www.wowprogress.com\/guild\/eu\/shattered-hand\/Cake+or+Death\/rating.tier10_25"},{"score":4759,"world_rank":16639,"area_rank":8826,"realm_rank":46,"name":"Go Ape","url":"http:\/\/www.wowprogress.com\/guild\/eu\/shattered-hand\/Go+Ape\/rating.tier10_25"},{"score":3967,"world_rank":17568,"area_rank":9356,"realm_rank":47,"name":"KilLeR bAbOoN TRoOPs","url":"http:\/\/www.wowprogress.com\/guild\/eu\/shattered-hand\/KilLeR+bAbOoN+TRoOPs\/rating.tier10_25"},{"score":3854,"world_rank":17726,"area_rank":9448,"realm_rank":48,"name":"Collapse","url":"http:\/\/www.wowprogress.com\/guild\/eu\/shattered-hand\/Collapse\/rating.tier10_25"},{"score":3486,"world_rank":18340,"area_rank":9802,"realm_rank":49,"name":"Sleepless Knights","url":"http:\/\/www.wowprogress.com\/guild\/eu\/shattered-hand\/Sleepless+Knights\/rating.tier10_25"},{"score":3452,"world_rank":18396,"area_rank":9838,"realm_rank":50,"name":"Intercept","url":"http:\/\/www.wowprogress.com\/guild\/eu\/shattered-hand\/Intercept\/rating.tier10_25"},{"score":3340,"world_rank":18585,"area_rank":9938,"realm_rank":51,"name":"Formula One","url":"http:\/\/www.wowprogress.com\/guild\/eu\/shattered-hand\/Formula+One\/rating.tier10_25"},{"score":3093,"world_rank":19140,"area_rank":10265,"realm_rank":52,"name":"Middle Aged Madness","url":"http:\/\/www.wowprogress.com\/guild\/eu\/shattered-hand\/Middle+Aged+Madness\/rating.tier10_25"},{"score":2971,"world_rank":19478,"area_rank":10465,"realm_rank":53,"name":"Nova prospekt","url":"http:\/\/www.wowprogress.com\/guild\/eu\/shattered-hand\/Nova+prospekt\/rating.tier10_25"},{"score":2853,"world_rank":19835,"area_rank":10687,"realm_rank":54,"name":"Mature Weekend Raiders","url":"http:\/\/www.wowprogress.com\/guild\/eu\/shattered-hand\/Mature+Weekend+Raiders\/rating.tier10_25"},{"score":2092,"world_rank":22547,"area_rank":12340,"realm_rank":55,"name":"Illuminati","url":"http:\/\/www.wowprogress.com\/guild\/eu\/shattered-hand\/Illuminati\/rating.tier10_25"},{"score":1968,"world_rank":23185,"area_rank":12722,"realm_rank":56,"name":"Slightly Behind","url":"http:\/\/www.wowprogress.com\/guild\/eu\/shattered-hand\/Slightly+Behind\/rating.tier10_25"},{"score":1836,"world_rank":23990,"area_rank":13206,"realm_rank":57,"name":"Who Dares Wins","url":"http:\/\/www.wowprogress.com\/guild\/eu\/shattered-hand\/Who+Dares+Wins\/rating.tier10_25"},{"score":1676,"world_rank":25128,"area_rank":13890,"realm_rank":58,"name":"Signed For Life","url":"http:\/\/www.wowprogress.com\/guild\/eu\/shattered-hand\/Signed+For+Life\/rating.tier10_25"},{"score":1580,"world_rank":25786,"area_rank":14259,"realm_rank":59,"name":"Unbroken","url":"http:\/\/www.wowprogress.com\/guild\/eu\/shattered-hand\/Unbroken\/rating.tier10_25"},{"score":1485,"world_rank":26448,"area_rank":14662,"realm_rank":60,"name":"Homesick","url":"http:\/\/www.wowprogress.com\/guild\/eu\/shattered-hand\/Homesick\/rating.tier10_25"},{"score":1400,"world_rank":26989,"area_rank":15008,"realm_rank":61,"name":"Maximum Testosterone","url":"http:\/\/www.wowprogress.com\/guild\/eu\/shattered-hand\/Maximum+Testosterone\/rating.tier10_25"},{"score":1395,"world_rank":27029,"area_rank":15033,"realm_rank":62,"name":"Aeternum","url":"http:\/\/www.wowprogress.com\/guild\/eu\/shattered-hand\/Aeternum\/rating.tier10_25"},{"score":1198,"world_rank":27880,"area_rank":15536,"realm_rank":63,"name":"Divine Intervention","url":"http:\/\/www.wowprogress.com\/guild\/eu\/shattered-hand\/Divine+Intervention\/rating.tier10_25"},{"score":990,"world_rank":28762,"area_rank":16000,"realm_rank":64,"name":"OMFGKITTENMEOWMEOW","url":"http:\/\/www.wowprogress.com\/guild\/eu\/shattered-hand\/OMFGKITTENMEOWMEOW\/rating.tier10_25"},{"score":872,"world_rank":29929,"area_rank":16596,"realm_rank":65,"name":"Wasted Generation","url":"http:\/\/www.wowprogress.com\/guild\/eu\/shattered-hand\/Wasted+Generation\/rating.tier10_25"},{"score":755,"world_rank":31809,"area_rank":17604,"realm_rank":66,"name":"The Family Legion","url":"http:\/\/www.wowprogress.com\/guild\/eu\/shattered-hand\/The+Family+Legion\/rating.tier10_25"},{"score":698,"world_rank":33123,"area_rank":18303,"realm_rank":67,"name":"Falass\u00eb N\u00fam\u00eba","url":"http:\/\/www.wowprogress.com\/guild\/eu\/shattered-hand\/Falass%C3%AB+N%C3%BAm%C3%ABa\/rating.tier10_25"},{"score":691,"world_rank":33284,"area_rank":18389,"realm_rank":68,"name":"Hollands Glorie","url":"http:\/\/www.wowprogress.com\/guild\/eu\/shattered-hand\/Hollands+Glorie\/rating.tier10_25"},{"score":690,"world_rank":33313,"area_rank":18406,"realm_rank":69,"name":"Chapter II","url":"http:\/\/www.wowprogress.com\/guild\/eu\/shattered-hand\/Chapter+II\/rating.tier10_25"},{"score":690,"world_rank":33335,"area_rank":18418,"realm_rank":70,"name":"Prowess","url":"http:\/\/www.wowprogress.com\/guild\/eu\/shattered-hand\/Prowess\/rating.tier10_25"},{"score":640,"world_rank":34712,"area_rank":19113,"realm_rank":71,"name":"Grumpy Old Men","url":"http:\/\/www.wowprogress.com\/guild\/eu\/shattered-hand\/Grumpy+Old+Men\/rating.tier10_25"},{"score":594,"world_rank":36085,"area_rank":19818,"realm_rank":72,"name":"Necrosis","url":"http:\/\/www.wowprogress.com\/guild\/eu\/shattered-hand\/Necrosis\/rating.tier10_25"},{"score":588,"world_rank":36304,"area_rank":19916,"realm_rank":73,"name":"Aphotic","url":"http:\/\/www.wowprogress.com\/guild\/eu\/shattered-hand\/Aphotic\/rating.tier10_25"},{"score":575,"world_rank":36734,"area_rank":20143,"realm_rank":74,"name":"Evolut\u00edon","url":"http:\/\/www.wowprogress.com\/guild\/eu\/shattered-hand\/Evolut%C3%ADon\/rating.tier10_25"},{"score":561,"world_rank":37140,"area_rank":20337,"realm_rank":75,"name":"The Dark Council","url":"http:\/\/www.wowprogress.com\/guild\/eu\/shattered-hand\/The+Dark+Council\/rating.tier10_25"},{"score":550,"world_rank":37634,"area_rank":20601,"realm_rank":76,"name":"Sagoland","url":"http:\/\/www.wowprogress.com\/guild\/eu\/shattered-hand\/Sagoland\/rating.tier10_25"},{"score":499,"world_rank":39460,"area_rank":21563,"realm_rank":77,"name":"The Dedicated Few","url":"http:\/\/www.wowprogress.com\/guild\/eu\/shattered-hand\/The+Dedicated+Few\/rating.tier10_25"},{"score":475,"world_rank":40238,"area_rank":21960,"realm_rank":78,"name":"Hymn","url":"http:\/\/www.wowprogress.com\/guild\/eu\/shattered-hand\/Hymn\/rating.tier10_25"},{"score":468,"world_rank":40511,"area_rank":22092,"realm_rank":79,"name":"Other Side","url":"http:\/\/www.wowprogress.com\/guild\/eu\/shattered-hand\/Other+Side\/rating.tier10_25"},{"score":454,"world_rank":41074,"area_rank":22360,"realm_rank":80,"name":"Ctrl Alt Del","url":"http:\/\/www.wowprogress.com\/guild\/eu\/shattered-hand\/Ctrl+Alt+Del\/rating.tier10_25"},{"score":451,"world_rank":41257,"area_rank":22437,"realm_rank":81,"name":"Blood and Glory","url":"http:\/\/www.wowprogress.com\/guild\/eu\/shattered-hand\/Blood+and+Glory\/rating.tier10_25"},{"score":450,"world_rank":41607,"area_rank":22597,"realm_rank":82,"name":"Kewpuh Stars","url":"http:\/\/www.wowprogress.com\/guild\/eu\/shattered-hand\/Kewpuh+Stars\/rating.tier10_25"},{"score":450,"world_rank":41882,"area_rank":22751,"realm_rank":83,"name":"SFA","url":"http:\/\/www.wowprogress.com\/guild\/eu\/shattered-hand\/SFA\/rating.tier10_25"},{"score":450,"world_rank":43365,"area_rank":23544,"realm_rank":84,"name":"Deformed","url":"http:\/\/www.wowprogress.com\/guild\/eu\/shattered-hand\/Deformed\/rating.tier10_25"},{"score":450,"world_rank":43414,"area_rank":23581,"realm_rank":85,"name":"Fredagsmys","url":"http:\/\/www.wowprogress.com\/guild\/eu\/shattered-hand\/Fredagsmys\/rating.tier10_25"},{"score":450,"world_rank":44019,"area_rank":23894,"realm_rank":86,"name":"Cataclysmic","url":"http:\/\/www.wowprogress.com\/guild\/eu\/shattered-hand\/Cataclysmic\/rating.tier10_25"},{"score":450,"world_rank":44137,"area_rank":23959,"realm_rank":87,"name":"Hell Spawns","url":"http:\/\/www.wowprogress.com\/guild\/eu\/shattered-hand\/Hell+Spawns\/rating.tier10_25"},{"score":406,"world_rank":44843,"area_rank":24391,"realm_rank":88,"name":"Obsidian Guard","url":"http:\/\/www.wowprogress.com\/guild\/eu\/shattered-hand\/Obsidian+Guard\/rating.tier10_25"},{"score":350,"world_rank":46188,"area_rank":25033,"realm_rank":89,"name":"Aurora Borealis","url":"http:\/\/www.wowprogress.com\/guild\/eu\/shattered-hand\/Aurora+Borealis\/rating.tier10_25"},{"score":250,"world_rank":48235,"area_rank":26112,"realm_rank":90,"name":"Dribbles","url":"http:\/\/www.wowprogress.com\/guild\/eu\/shattered-hand\/Dribbles\/rating.tier10_25"},{"score":250,"world_rank":48661,"area_rank":26295,"realm_rank":91,"name":"By Crayon Be Purged","url":"http:\/\/www.wowprogress.com\/guild\/eu\/shattered-hand\/By+Crayon+Be+Purged\/rating.tier10_25"},{"score":250,"world_rank":49162,"area_rank":26544,"realm_rank":92,"name":"Generated","url":"http:\/\/www.wowprogress.com\/guild\/eu\/shattered-hand\/Generated\/rating.tier10_25"},{"score":250,"world_rank":50285,"area_rank":27057,"realm_rank":93,"name":"Plan Bee","url":"http:\/\/www.wowprogress.com\/guild\/eu\/shattered-hand\/Plan+Bee\/rating.tier10_25"},{"score":250,"world_rank":50470,"area_rank":27153,"realm_rank":94,"name":"Nordic United","url":"http:\/\/www.wowprogress.com\/guild\/eu\/shattered-hand\/Nordic+United\/rating.tier10_25"},{"score":250,"world_rank":50540,"area_rank":27194,"realm_rank":95,"name":"Archaeologists","url":"http:\/\/www.wowprogress.com\/guild\/eu\/shattered-hand\/Archaeologists\/rating.tier10_25"},{"score":250,"world_rank":51125,"area_rank":27476,"realm_rank":96,"name":"Xyth","url":"http:\/\/www.wowprogress.com\/guild\/eu\/shattered-hand\/Xyth\/rating.tier10_25"},{"score":250,"world_rank":51620,"area_rank":27756,"realm_rank":97,"name":"Ancient Nation","url":"http:\/\/www.wowprogress.com\/guild\/eu\/shattered-hand\/Ancient+Nation\/rating.tier10_25"}]