[{"score":3750000,"world_rank":211,"area_rank":31,"realm_rank":1,"name":"\uc774\ud654\uc5ec\ub300 \ud1a0\ubaa9\uacf5\ud559\uacfc \uac1c\uadf8\ub3d9\uc544\ub9ac","url":"http:\/\/www.wowprogress.com\/guild\/kr\/windrunner\/%EC%9D%B4%ED%99%94%EC%97%AC%EB%8C%80+%ED%86%A0%EB%AA%A9%EA%B3%B5%ED%95%99%EA%B3%BC+%EA%B0%9C%EA%B7%B8%EB%8F%99%EC%95%84%EB%A6%AC\/rating.tier15_10"},{"score":3750000,"world_rank":300,"area_rank":41,"realm_rank":2,"name":"\ubd88\uaf43\ucc98\ub7fc","url":"http:\/\/www.wowprogress.com\/guild\/kr\/windrunner\/%EB%B6%88%EA%BD%83%EC%B2%98%EB%9F%BC\/rating.tier15_10"},{"score":3750000,"world_rank":554,"area_rank":67,"realm_rank":3,"name":"\ucc9c \uc77c","url":"http:\/\/www.wowprogress.com\/guild\/kr\/windrunner\/%EC%B2%9C+%EC%9D%BC\/rating.tier15_10"},{"score":3750000,"world_rank":2084,"area_rank":121,"realm_rank":4,"name":"Bustahz","url":"http:\/\/www.wowprogress.com\/guild\/kr\/windrunner\/Bustahz\/rating.tier15_10"},{"score":825000,"world_rank":5532,"area_rank":204,"realm_rank":5,"name":"\ub9c9\ub0b4","url":"http:\/\/www.wowprogress.com\/guild\/kr\/windrunner\/%EB%A7%89%EB%82%B4\/rating.tier15_10"},{"score":825000,"world_rank":5576,"area_rank":209,"realm_rank":6,"name":"The Dawn","url":"http:\/\/www.wowprogress.com\/guild\/kr\/windrunner\/The+Dawn\/rating.tier15_10"},{"score":650000,"world_rank":7253,"area_rank":233,"realm_rank":7,"name":"\ub808\ub4dc\uc81c\ud50c\ub9b0","url":"http:\/\/www.wowprogress.com\/guild\/kr\/windrunner\/%EB%A0%88%EB%93%9C%EC%A0%9C%ED%94%8C%EB%A6%B0\/rating.tier15_10"},{"score":600000,"world_rank":8289,"area_rank":269,"realm_rank":8,"name":"ShowMeTheMoney","url":"http:\/\/www.wowprogress.com\/guild\/kr\/windrunner\/ShowMeTheMoney\/rating.tier15_10"},{"score":525000,"world_rank":8987,"area_rank":282,"realm_rank":9,"name":"\uc2e0\ub4e4\uc758\ud669\ud63c","url":"http:\/\/www.wowprogress.com\/guild\/kr\/windrunner\/%EC%8B%A0%EB%93%A4%EC%9D%98%ED%99%A9%ED%98%BC\/rating.tier15_10"},{"score":525000,"world_rank":9009,"area_rank":290,"realm_rank":10,"name":"\ucc9c\uc0c1\uc758\ucc2c\uac00","url":"http:\/\/www.wowprogress.com\/guild\/kr\/windrunner\/%EC%B2%9C%EC%83%81%EC%9D%98%EC%B0%AC%EA%B0%80\/rating.tier15_10"},{"score":500000,"world_rank":9284,"area_rank":315,"realm_rank":11,"name":"\uc545\ub9c8\uc758\uc0c1\uc810\uc5d0\uc11c\uac00\uc7a5\ube44\uc2fc\ubb3c\uac74\uc740\uc88c\uc808","url":"http:\/\/www.wowprogress.com\/guild\/kr\/windrunner\/%EC%95%85%EB%A7%88%EC%9D%98%EC%83%81%EC%A0%90%EC%97%90%EC%84%9C%EA%B0%80%EC%9E%A5%EB%B9%84%EC%8B%BC%EB%AC%BC%EA%B1%B4%EC%9D%80%EC%A2%8C%EC%A0%88\/rating.tier15_10"},{"score":400000,"world_rank":9714,"area_rank":332,"realm_rank":12,"name":"Pluie de Etoiles","url":"http:\/\/www.wowprogress.com\/guild\/kr\/windrunner\/Pluie+de+Etoiles\/rating.tier15_10"},{"score":300000,"world_rank":10607,"area_rank":372,"realm_rank":13,"name":"\uc5bc\ub77c\uc774\uc5b8\uc2a4\ub3d9\ub9f9","url":"http:\/\/www.wowprogress.com\/guild\/kr\/windrunner\/%EC%96%BC%EB%9D%BC%EC%9D%B4%EC%96%B8%EC%8A%A4%EB%8F%99%EB%A7%B9\/rating.tier15_10"},{"score":225000,"world_rank":11505,"area_rank":408,"realm_rank":14,"name":"Death Squad","url":"http:\/\/www.wowprogress.com\/guild\/kr\/windrunner\/Death+Squad\/rating.tier15_10"},{"score":175000,"world_rank":12938,"area_rank":438,"realm_rank":15,"name":"\ud655\uace0\ud55c\ub3d9\ub9f9","url":"http:\/\/www.wowprogress.com\/guild\/kr\/windrunner\/%ED%99%95%EA%B3%A0%ED%95%9C%EB%8F%99%EB%A7%B9\/rating.tier15_10"},{"score":150000,"world_rank":13702,"area_rank":463,"realm_rank":16,"name":"\ud568\uaed8\ud558\uba74 \uc990\uac70\uc6b4","url":"http:\/\/www.wowprogress.com\/guild\/kr\/windrunner\/%ED%95%A8%EA%BB%98%ED%95%98%EB%A9%B4+%EC%A6%90%EA%B1%B0%EC%9A%B4\/rating.tier15_10"},{"score":125000,"world_rank":14528,"area_rank":489,"realm_rank":17,"name":"Band of Alliance","url":"http:\/\/www.wowprogress.com\/guild\/kr\/windrunner\/Band+of+Alliance\/rating.tier15_10"},{"score":125000,"world_rank":14627,"area_rank":497,"realm_rank":18,"name":"\ubc14\ub098\ub098\ub77c\ub5bc","url":"http:\/\/www.wowprogress.com\/guild\/kr\/windrunner\/%EB%B0%94%EB%82%98%EB%82%98%EB%9D%BC%EB%96%BC\/rating.tier15_10"},{"score":100000,"world_rank":16300,"area_rank":522,"realm_rank":19,"name":"\uacf5\ub300 \ud30c\uad34\uc790","url":"http:\/\/www.wowprogress.com\/guild\/kr\/windrunner\/%EA%B3%B5%EB%8C%80+%ED%8C%8C%EA%B4%B4%EC%9E%90\/rating.tier15_10"},{"score":100000,"world_rank":16387,"area_rank":524,"realm_rank":20,"name":"Mysterious House","url":"http:\/\/www.wowprogress.com\/guild\/kr\/windrunner\/Mysterious+House\/rating.tier15_10"},{"score":75000,"world_rank":17692,"area_rank":573,"realm_rank":21,"name":"\uac10\uc790\ubc2d\uc5d0\uac14\ub294\ub370\ub4f1\uc5d0\ud759\uc774\uc65c\ubb3b\uc5b4","url":"http:\/\/www.wowprogress.com\/guild\/kr\/windrunner\/%EA%B0%90%EC%9E%90%EB%B0%AD%EC%97%90%EA%B0%94%EB%8A%94%EB%8D%B0%EB%93%B1%EC%97%90%ED%9D%99%EC%9D%B4%EC%99%9C%EB%AC%BB%EC%96%B4\/rating.tier15_10"},{"score":75000,"world_rank":17888,"area_rank":582,"realm_rank":22,"name":"\uc601\uc6c5\uc758 \uc804\uc124","url":"http:\/\/www.wowprogress.com\/guild\/kr\/windrunner\/%EC%98%81%EC%9B%85%EC%9D%98+%EC%A0%84%EC%84%A4\/rating.tier15_10"},{"score":75000,"world_rank":19047,"area_rank":607,"realm_rank":23,"name":"\uc5bc\ub77c\uc774\uc5b8\uc2a4 \uccad\ub144\ud68c","url":"http:\/\/www.wowprogress.com\/guild\/kr\/windrunner\/%EC%96%BC%EB%9D%BC%EC%9D%B4%EC%96%B8%EC%8A%A4+%EC%B2%AD%EB%85%84%ED%9A%8C\/rating.tier15_10"},{"score":75000,"world_rank":19577,"area_rank":619,"realm_rank":24,"name":"\ub208\uc18d\uc758 \uaf43","url":"http:\/\/www.wowprogress.com\/guild\/kr\/windrunner\/%EB%88%88%EC%86%8D%EC%9D%98+%EA%BD%83\/rating.tier15_10"},{"score":50000,"world_rank":20563,"area_rank":637,"realm_rank":25,"name":"\uc18c\ub354\ube44\uc2a4","url":"http:\/\/www.wowprogress.com\/guild\/kr\/windrunner\/%EC%86%8C%EB%8D%94%EB%B9%84%EC%8A%A4\/rating.tier15_10"},{"score":21000,"world_rank":22038,"area_rank":734,"realm_rank":26,"name":"\uc120\uc774\uc640 \uc9c0\uc544","url":"http:\/\/www.wowprogress.com\/guild\/kr\/windrunner\/%EC%84%A0%EC%9D%B4%EC%99%80+%EC%A7%80%EC%95%84\/rating.tier15_10"},{"score":21000,"world_rank":22131,"area_rank":736,"realm_rank":27,"name":"\ub9de\ub294\uc990\uac70\uc6c0\ub54c\ub9ac\ub294\uae30\uc068","url":"http:\/\/www.wowprogress.com\/guild\/kr\/windrunner\/%EB%A7%9E%EB%8A%94%EC%A6%90%EA%B1%B0%EC%9B%80%EB%95%8C%EB%A6%AC%EB%8A%94%EA%B8%B0%EC%81%A8\/rating.tier15_10"},{"score":21000,"world_rank":22266,"area_rank":740,"realm_rank":28,"name":"\ucd08\uc2ec\ucd08\uc2ec","url":"http:\/\/www.wowprogress.com\/guild\/kr\/windrunner\/%EC%B4%88%EC%8B%AC%EC%B4%88%EC%8B%AC\/rating.tier15_10"},{"score":21000,"world_rank":22300,"area_rank":741,"realm_rank":29,"name":"\ub9c8\ub3c4\ud328\ubc00\ub9ac","url":"http:\/\/www.wowprogress.com\/guild\/kr\/windrunner\/%EB%A7%88%EB%8F%84%ED%8C%A8%EB%B0%80%EB%A6%AC\/rating.tier15_10"},{"score":21000,"world_rank":22525,"area_rank":749,"realm_rank":30,"name":"\ud558\ub298\uc758 \uc2ec\ud310","url":"http:\/\/www.wowprogress.com\/guild\/kr\/windrunner\/%ED%95%98%EB%8A%98%EC%9D%98+%EC%8B%AC%ED%8C%90\/rating.tier15_10"},{"score":21000,"world_rank":23730,"area_rank":766,"realm_rank":31,"name":"\ub0b4\ub9d8\ub300\ub85c \uc0b4\uaebc\uc57c","url":"http:\/\/www.wowprogress.com\/guild\/kr\/windrunner\/%EB%82%B4%EB%A7%98%EB%8C%80%EB%A1%9C+%EC%82%B4%EA%BA%BC%EC%95%BC\/rating.tier15_10"},{"score":16500,"world_rank":29543,"area_rank":845,"realm_rank":32,"name":"\ud5e8\ub378\uacfc\uadf8\ub7ac\ub300","url":"http:\/\/www.wowprogress.com\/guild\/kr\/windrunner\/%ED%97%A8%EB%8D%B8%EA%B3%BC%EA%B7%B8%EB%9E%AC%EB%8C%80\/rating.tier15_10"},{"score":13500,"world_rank":31480,"area_rank":891,"realm_rank":33,"name":"Nice Day","url":"http:\/\/www.wowprogress.com\/guild\/kr\/windrunner\/Nice+Day\/rating.tier15_10"},{"score":13500,"world_rank":31635,"area_rank":892,"realm_rank":34,"name":"\uc5ec\uba85\uc744 \uc5ec\ub294 \uc0ac\ub78c\ub4e4","url":"http:\/\/www.wowprogress.com\/guild\/kr\/windrunner\/%EC%97%AC%EB%AA%85%EC%9D%84+%EC%97%AC%EB%8A%94+%EC%82%AC%EB%9E%8C%EB%93%A4\/rating.tier15_10"},{"score":12000,"world_rank":32651,"area_rank":899,"realm_rank":35,"name":"LIFE GOES ON","url":"http:\/\/www.wowprogress.com\/guild\/kr\/windrunner\/LIFE+GOES+ON\/rating.tier15_10"},{"score":12000,"world_rank":35444,"area_rank":912,"realm_rank":36,"name":"\ubfd4\ud53c\ub9ac\uc18c\ub9ac\ub97c \ub192\uac8c\ud558\uace0 \uc9d0\uc2b9\uac19\uc774 \ud3ec\ud6a8\ud574\ub77c","url":"http:\/\/www.wowprogress.com\/guild\/kr\/windrunner\/%EB%BF%94%ED%94%BC%EB%A6%AC%EC%86%8C%EB%A6%AC%EB%A5%BC+%EB%86%92%EA%B2%8C%ED%95%98%EA%B3%A0+%EC%A7%90%EC%8A%B9%EA%B0%99%EC%9D%B4+%ED%8F%AC%ED%9A%A8%ED%95%B4%EB%9D%BC\/rating.tier15_10"},{"score":10500,"world_rank":35677,"area_rank":923,"realm_rank":37,"name":"\ub2c8\ub625\uaf2c\ub97c\uc624\uadf8\ub9ac\ub9c8","url":"http:\/\/www.wowprogress.com\/guild\/kr\/windrunner\/%EB%8B%88%EB%98%A5%EA%BC%AC%EB%A5%BC%EC%98%A4%EA%B7%B8%EB%A6%AC%EB%A7%88\/rating.tier15_10"},{"score":9000,"world_rank":36819,"area_rank":953,"realm_rank":38,"name":"For The Kingdom","url":"http:\/\/www.wowprogress.com\/guild\/kr\/windrunner\/For+The+Kingdom\/rating.tier15_10"},{"score":7500,"world_rank":40624,"area_rank":982,"realm_rank":39,"name":"\ub9c8\ub9c8","url":"http:\/\/www.wowprogress.com\/guild\/kr\/windrunner\/%EB%A7%88%EB%A7%88\/rating.tier15_10"},{"score":4500,"world_rank":43165,"area_rank":1019,"realm_rank":40,"name":"\uc640\uc77c\ub4dc\ud574\uba38","url":"http:\/\/www.wowprogress.com\/guild\/kr\/windrunner\/%EC%99%80%EC%9D%BC%EB%93%9C%ED%95%B4%EB%A8%B8\/rating.tier15_10"},{"score":4500,"world_rank":43608,"area_rank":1022,"realm_rank":41,"name":"John Nase","url":"http:\/\/www.wowprogress.com\/guild\/kr\/windrunner\/John+Nase\/rating.tier15_10"},{"score":4500,"world_rank":44952,"area_rank":1026,"realm_rank":42,"name":"\uad11\uac1c\ud1a0\ub300\uc655","url":"http:\/\/www.wowprogress.com\/guild\/kr\/windrunner\/%EA%B4%91%EA%B0%9C%ED%86%A0%EB%8C%80%EC%99%95\/rating.tier15_10"},{"score":500,"world_rank":53766,"area_rank":1089,"realm_rank":43,"name":"The Joker","url":"http:\/\/www.wowprogress.com\/guild\/kr\/windrunner\/The+Joker\/rating.tier15_10"}]