[{"score":1500000,"world_rank":3065,"area_rank":960,"realm_rank":1,"name":"Voodoo","url":"http:\/\/www.wowprogress.com\/guild\/us\/archimonde\/Voodoo\/rating.ach"},{"score":975000,"world_rank":3917,"area_rank":1164,"realm_rank":2,"name":"The Ancient Order","url":"http:\/\/www.wowprogress.com\/guild\/us\/archimonde\/The+Ancient+Order\/rating.ach"},{"score":825000,"world_rank":7010,"area_rank":2176,"realm_rank":3,"name":"Pseudo Guild","url":"http:\/\/www.wowprogress.com\/guild\/us\/archimonde\/Pseudo+Guild\/rating.ach"},{"score":750000,"world_rank":9426,"area_rank":3014,"realm_rank":4,"name":"Archetype","url":"http:\/\/www.wowprogress.com\/guild\/us\/archimonde\/Archetype\/rating.ach"},{"score":475000,"world_rank":14174,"area_rank":4637,"realm_rank":5,"name":"Flux","url":"http:\/\/www.wowprogress.com\/guild\/us\/archimonde\/Flux\/rating.ach"},{"score":450000,"world_rank":14779,"area_rank":4826,"realm_rank":6,"name":"Ashes of Proven Healers","url":"http:\/\/www.wowprogress.com\/guild\/us\/archimonde\/Ashes+of+Proven+Healers\/rating.ach"},{"score":150000,"world_rank":19219,"area_rank":6360,"realm_rank":7,"name":"SheTookItAllButWoW","url":"http:\/\/www.wowprogress.com\/guild\/us\/archimonde\/SheTookItAllButWoW\/rating.ach"},{"score":50000,"world_rank":22506,"area_rank":7516,"realm_rank":8,"name":"Final Destiny","url":"http:\/\/www.wowprogress.com\/guild\/us\/archimonde\/Final+Destiny\/rating.ach"},{"score":24000,"world_rank":28818,"area_rank":10125,"realm_rank":9,"name":"Sacred Silver Blades","url":"http:\/\/www.wowprogress.com\/guild\/us\/archimonde\/Sacred+Silver+Blades\/rating.ach"},{"score":19500,"world_rank":35423,"area_rank":12677,"realm_rank":10,"name":"Prototype","url":"http:\/\/www.wowprogress.com\/guild\/us\/archimonde\/Prototype\/rating.ach"},{"score":19500,"world_rank":35653,"area_rank":12763,"realm_rank":11,"name":"Serpents","url":"http:\/\/www.wowprogress.com\/guild\/us\/archimonde\/Serpents\/rating.ach"},{"score":15000,"world_rank":40355,"area_rank":14509,"realm_rank":12,"name":"Blood of the Fallen","url":"http:\/\/www.wowprogress.com\/guild\/us\/archimonde\/Blood+of+the+Fallen\/rating.ach"},{"score":7000,"world_rank":44904,"area_rank":16376,"realm_rank":13,"name":"MoneyInTheBank","url":"http:\/\/www.wowprogress.com\/guild\/us\/archimonde\/MoneyInTheBank\/rating.ach"},{"score":1500,"world_rank":48226,"area_rank":17787,"realm_rank":14,"name":"The Indicted","url":"http:\/\/www.wowprogress.com\/guild\/us\/archimonde\/The+Indicted\/rating.ach"}]