[{"score":2467778,"world_rank":727,"area_rank":170,"realm_rank":1,"name":"Sleepless Knights","url":"http:\/\/www.wowprogress.com\/guild\/us\/bronzebeard\/Sleepless+Knights\/rating.tier11.ach"},{"score":1918333,"world_rank":1360,"area_rank":359,"realm_rank":2,"name":"The Feral Aggressors","url":"http:\/\/www.wowprogress.com\/guild\/us\/bronzebeard\/The+Feral+Aggressors\/rating.tier11.ach"},{"score":767777,"world_rank":4377,"area_rank":1226,"realm_rank":3,"name":"Something Wicked","url":"http:\/\/www.wowprogress.com\/guild\/us\/bronzebeard\/Something+Wicked\/rating.tier11.ach"},{"score":582222,"world_rank":6053,"area_rank":1754,"realm_rank":4,"name":"My Target Please","url":"http:\/\/www.wowprogress.com\/guild\/us\/bronzebeard\/My+Target+Please\/rating.tier11.ach"},{"score":500001,"world_rank":7211,"area_rank":2125,"realm_rank":5,"name":"Grand Theft Kodo","url":"http:\/\/www.wowprogress.com\/guild\/us\/bronzebeard\/Grand+Theft+Kodo\/rating.tier11.ach"},{"score":362778,"world_rank":10027,"area_rank":3083,"realm_rank":6,"name":"Ominous","url":"http:\/\/www.wowprogress.com\/guild\/us\/bronzebeard\/Ominous\/rating.tier11.ach"},{"score":332778,"world_rank":10808,"area_rank":3333,"realm_rank":7,"name":"Higher Calling","url":"http:\/\/www.wowprogress.com\/guild\/us\/bronzebeard\/Higher+Calling\/rating.tier11.ach"},{"score":319444,"world_rank":11141,"area_rank":3443,"realm_rank":8,"name":"Serenity Knights","url":"http:\/\/www.wowprogress.com\/guild\/us\/bronzebeard\/Serenity+Knights\/rating.tier11.ach"},{"score":276111,"world_rank":12149,"area_rank":3775,"realm_rank":9,"name":"Paragon","url":"http:\/\/www.wowprogress.com\/guild\/us\/bronzebeard\/Paragon\/rating.tier11.ach"},{"score":266666,"world_rank":12373,"area_rank":3861,"realm_rank":10,"name":"Coherence","url":"http:\/\/www.wowprogress.com\/guild\/us\/bronzebeard\/Coherence\/rating.tier11.ach"},{"score":208888,"world_rank":14146,"area_rank":4505,"realm_rank":11,"name":"More Chaos","url":"http:\/\/www.wowprogress.com\/guild\/us\/bronzebeard\/More+Chaos\/rating.tier11.ach"},{"score":176666,"world_rank":15184,"area_rank":4848,"realm_rank":12,"name":"Resurrection","url":"http:\/\/www.wowprogress.com\/guild\/us\/bronzebeard\/Resurrection\/rating.tier11.ach"},{"score":170000,"world_rank":15399,"area_rank":4930,"realm_rank":13,"name":"Balance","url":"http:\/\/www.wowprogress.com\/guild\/us\/bronzebeard\/Balance\/rating.tier11.ach"},{"score":161667,"world_rank":15637,"area_rank":5011,"realm_rank":14,"name":"Minor Threat","url":"http:\/\/www.wowprogress.com\/guild\/us\/bronzebeard\/Minor+Threat\/rating.tier11.ach"},{"score":161111,"world_rank":15658,"area_rank":5023,"realm_rank":15,"name":"Swing Shift","url":"http:\/\/www.wowprogress.com\/guild\/us\/bronzebeard\/Swing+Shift\/rating.tier11.ach"},{"score":116111,"world_rank":17460,"area_rank":5681,"realm_rank":16,"name":"Requiem","url":"http:\/\/www.wowprogress.com\/guild\/us\/bronzebeard\/Requiem\/rating.tier11.ach"},{"score":110000,"world_rank":17988,"area_rank":5882,"realm_rank":17,"name":"Tyranny","url":"http:\/\/www.wowprogress.com\/guild\/us\/bronzebeard\/Tyranny\/rating.tier11.ach"},{"score":100000,"world_rank":18965,"area_rank":6243,"realm_rank":18,"name":"Cascaders","url":"http:\/\/www.wowprogress.com\/guild\/us\/bronzebeard\/Cascaders\/rating.tier11.ach"},{"score":67778,"world_rank":20886,"area_rank":6977,"realm_rank":19,"name":"Radical Dreamers","url":"http:\/\/www.wowprogress.com\/guild\/us\/bronzebeard\/Radical+Dreamers\/rating.tier11.ach"},{"score":64444,"world_rank":21167,"area_rank":7112,"realm_rank":20,"name":"Unchained","url":"http:\/\/www.wowprogress.com\/guild\/us\/bronzebeard\/Unchained\/rating.tier11.ach"},{"score":50000,"world_rank":22697,"area_rank":7770,"realm_rank":21,"name":"Dissonance","url":"http:\/\/www.wowprogress.com\/guild\/us\/bronzebeard\/Dissonance\/rating.tier11.ach"},{"score":50000,"world_rank":22778,"area_rank":7822,"realm_rank":22,"name":"Apex","url":"http:\/\/www.wowprogress.com\/guild\/us\/bronzebeard\/Apex\/rating.tier11.ach"},{"score":50000,"world_rank":24321,"area_rank":8475,"realm_rank":23,"name":"Triumph","url":"http:\/\/www.wowprogress.com\/guild\/us\/bronzebeard\/Triumph\/rating.tier11.ach"},{"score":50000,"world_rank":24514,"area_rank":8553,"realm_rank":24,"name":"Pro By Association","url":"http:\/\/www.wowprogress.com\/guild\/us\/bronzebeard\/Pro+By+Association\/rating.tier11.ach"},{"score":50000,"world_rank":24975,"area_rank":8754,"realm_rank":25,"name":"History of Violence","url":"http:\/\/www.wowprogress.com\/guild\/us\/bronzebeard\/History+of+Violence\/rating.tier11.ach"},{"score":50000,"world_rank":25273,"area_rank":8890,"realm_rank":26,"name":"Reckoning","url":"http:\/\/www.wowprogress.com\/guild\/us\/bronzebeard\/Reckoning\/rating.tier11.ach"},{"score":50000,"world_rank":25793,"area_rank":9085,"realm_rank":27,"name":"Punch N Pie","url":"http:\/\/www.wowprogress.com\/guild\/us\/bronzebeard\/Punch+N+Pie\/rating.tier11.ach"},{"score":50000,"world_rank":27058,"area_rank":9539,"realm_rank":28,"name":"Cake or Death","url":"http:\/\/www.wowprogress.com\/guild\/us\/bronzebeard\/Cake+or+Death\/rating.tier11.ach"},{"score":16523,"world_rank":30515,"area_rank":10837,"realm_rank":29,"name":"Famous Last Words","url":"http:\/\/www.wowprogress.com\/guild\/us\/bronzebeard\/Famous+Last+Words\/rating.tier11.ach"},{"score":15000,"world_rank":32725,"area_rank":11784,"realm_rank":30,"name":"Straw Hat Pirates","url":"http:\/\/www.wowprogress.com\/guild\/us\/bronzebeard\/Straw+Hat+Pirates\/rating.tier11.ach"},{"score":14901,"world_rank":32955,"area_rank":11888,"realm_rank":31,"name":"Icefall","url":"http:\/\/www.wowprogress.com\/guild\/us\/bronzebeard\/Icefall\/rating.tier11.ach"},{"score":14873,"world_rank":33012,"area_rank":11910,"realm_rank":32,"name":"Unyielding","url":"http:\/\/www.wowprogress.com\/guild\/us\/bronzebeard\/Unyielding\/rating.tier11.ach"},{"score":14561,"world_rank":33720,"area_rank":12235,"realm_rank":33,"name":"Angels on Guard","url":"http:\/\/www.wowprogress.com\/guild\/us\/bronzebeard\/Angels+on+Guard\/rating.tier11.ach"},{"score":14472,"world_rank":33934,"area_rank":12334,"realm_rank":34,"name":"Prevalence","url":"http:\/\/www.wowprogress.com\/guild\/us\/bronzebeard\/Prevalence\/rating.tier11.ach"},{"score":14111,"world_rank":34876,"area_rank":12705,"realm_rank":35,"name":"What Fire","url":"http:\/\/www.wowprogress.com\/guild\/us\/bronzebeard\/What+Fire\/rating.tier11.ach"},{"score":14016,"world_rank":35111,"area_rank":12805,"realm_rank":36,"name":"Coconut Wireless","url":"http:\/\/www.wowprogress.com\/guild\/us\/bronzebeard\/Coconut+Wireless\/rating.tier11.ach"},{"score":13995,"world_rank":35169,"area_rank":12832,"realm_rank":37,"name":"Leth\u00e3lity","url":"http:\/\/www.wowprogress.com\/guild\/us\/bronzebeard\/Leth%C3%A3lity\/rating.tier11.ach"},{"score":13963,"world_rank":35247,"area_rank":12866,"realm_rank":38,"name":"Dafunk","url":"http:\/\/www.wowprogress.com\/guild\/us\/bronzebeard\/Dafunk\/rating.tier11.ach"},{"score":13795,"world_rank":35712,"area_rank":13060,"realm_rank":39,"name":"Pure","url":"http:\/\/www.wowprogress.com\/guild\/us\/bronzebeard\/Pure\/rating.tier11.ach"},{"score":13734,"world_rank":35882,"area_rank":13137,"realm_rank":40,"name":"Raid Zone","url":"http:\/\/www.wowprogress.com\/guild\/us\/bronzebeard\/Raid+Zone\/rating.tier11.ach"},{"score":13328,"world_rank":36899,"area_rank":13574,"realm_rank":41,"name":"Nothing to Lose","url":"http:\/\/www.wowprogress.com\/guild\/us\/bronzebeard\/Nothing+to+Lose\/rating.tier11.ach"},{"score":13171,"world_rank":37301,"area_rank":13760,"realm_rank":42,"name":"Catalyst","url":"http:\/\/www.wowprogress.com\/guild\/us\/bronzebeard\/Catalyst\/rating.tier11.ach"},{"score":13084,"world_rank":37506,"area_rank":13859,"realm_rank":43,"name":"l Know Where You Hearth","url":"http:\/\/www.wowprogress.com\/guild\/us\/bronzebeard\/l+Know+Where+You+Hearth\/rating.tier11.ach"},{"score":12911,"world_rank":37969,"area_rank":14063,"realm_rank":44,"name":"The Censored Linguists","url":"http:\/\/www.wowprogress.com\/guild\/us\/bronzebeard\/The+Censored+Linguists\/rating.tier11.ach"},{"score":12628,"world_rank":38741,"area_rank":14368,"realm_rank":45,"name":"Army of Helaman","url":"http:\/\/www.wowprogress.com\/guild\/us\/bronzebeard\/Army+of+Helaman\/rating.tier11.ach"},{"score":12550,"world_rank":38955,"area_rank":14465,"realm_rank":46,"name":"The Nightfall","url":"http:\/\/www.wowprogress.com\/guild\/us\/bronzebeard\/The+Nightfall\/rating.tier11.ach"},{"score":12533,"world_rank":39010,"area_rank":14488,"realm_rank":47,"name":"Nightbane","url":"http:\/\/www.wowprogress.com\/guild\/us\/bronzebeard\/Nightbane\/rating.tier11.ach"},{"score":12439,"world_rank":39287,"area_rank":14602,"realm_rank":48,"name":"Rock Hard","url":"http:\/\/www.wowprogress.com\/guild\/us\/bronzebeard\/Rock+Hard\/rating.tier11.ach"},{"score":12417,"world_rank":39367,"area_rank":14629,"realm_rank":49,"name":"Overcome","url":"http:\/\/www.wowprogress.com\/guild\/us\/bronzebeard\/Overcome\/rating.tier11.ach"},{"score":12250,"world_rank":39861,"area_rank":14850,"realm_rank":50,"name":"Daughters OfThe Alliance","url":"http:\/\/www.wowprogress.com\/guild\/us\/bronzebeard\/Daughters+OfThe+Alliance\/rating.tier11.ach"},{"score":11506,"world_rank":42126,"area_rank":15796,"realm_rank":51,"name":"Half Baked","url":"http:\/\/www.wowprogress.com\/guild\/us\/bronzebeard\/Half+Baked\/rating.tier11.ach"},{"score":11445,"world_rank":42307,"area_rank":15873,"realm_rank":52,"name":"Killing Time","url":"http:\/\/www.wowprogress.com\/guild\/us\/bronzebeard\/Killing+Time\/rating.tier11.ach"},{"score":11414,"world_rank":42414,"area_rank":15924,"realm_rank":53,"name":"Nefarious","url":"http:\/\/www.wowprogress.com\/guild\/us\/bronzebeard\/Nefarious\/rating.tier11.ach"},{"score":11385,"world_rank":42506,"area_rank":15963,"realm_rank":54,"name":"The Buy More","url":"http:\/\/www.wowprogress.com\/guild\/us\/bronzebeard\/The+Buy+More\/rating.tier11.ach"},{"score":11244,"world_rank":42973,"area_rank":16158,"realm_rank":55,"name":"Kaos Theory","url":"http:\/\/www.wowprogress.com\/guild\/us\/bronzebeard\/Kaos+Theory\/rating.tier11.ach"},{"score":11199,"world_rank":43122,"area_rank":16225,"realm_rank":56,"name":"Legion of Sacred Trust","url":"http:\/\/www.wowprogress.com\/guild\/us\/bronzebeard\/Legion+of+Sacred+Trust\/rating.tier11.ach"},{"score":10961,"world_rank":43954,"area_rank":16574,"realm_rank":57,"name":"Milkshake Factory","url":"http:\/\/www.wowprogress.com\/guild\/us\/bronzebeard\/Milkshake+Factory\/rating.tier11.ach"},{"score":10900,"world_rank":44167,"area_rank":16665,"realm_rank":58,"name":"Formerly Unguilded","url":"http:\/\/www.wowprogress.com\/guild\/us\/bronzebeard\/Formerly+Unguilded\/rating.tier11.ach"},{"score":10612,"world_rank":45143,"area_rank":17091,"realm_rank":59,"name":"Silent Vendetta","url":"http:\/\/www.wowprogress.com\/guild\/us\/bronzebeard\/Silent+Vendetta\/rating.tier11.ach"},{"score":10367,"world_rank":46030,"area_rank":17471,"realm_rank":60,"name":"Phoenix Ascended","url":"http:\/\/www.wowprogress.com\/guild\/us\/bronzebeard\/Phoenix+Ascended\/rating.tier11.ach"},{"score":10355,"world_rank":46067,"area_rank":17486,"realm_rank":61,"name":"Scurvy","url":"http:\/\/www.wowprogress.com\/guild\/us\/bronzebeard\/Scurvy\/rating.tier11.ach"},{"score":10227,"world_rank":46529,"area_rank":17699,"realm_rank":62,"name":"Primogeniture","url":"http:\/\/www.wowprogress.com\/guild\/us\/bronzebeard\/Primogeniture\/rating.tier11.ach"},{"score":10206,"world_rank":46600,"area_rank":17733,"realm_rank":63,"name":"Forgotten Redemption","url":"http:\/\/www.wowprogress.com\/guild\/us\/bronzebeard\/Forgotten+Redemption\/rating.tier11.ach"},{"score":10160,"world_rank":46778,"area_rank":17820,"realm_rank":64,"name":"Shenlong","url":"http:\/\/www.wowprogress.com\/guild\/us\/bronzebeard\/Shenlong\/rating.tier11.ach"},{"score":10017,"world_rank":47244,"area_rank":18034,"realm_rank":65,"name":"Bloodline","url":"http:\/\/www.wowprogress.com\/guild\/us\/bronzebeard\/Bloodline\/rating.tier11.ach"},{"score":10011,"world_rank":47267,"area_rank":18046,"realm_rank":66,"name":"Deliverance","url":"http:\/\/www.wowprogress.com\/guild\/us\/bronzebeard\/Deliverance\/rating.tier11.ach"},{"score":9966,"world_rank":47410,"area_rank":18113,"realm_rank":67,"name":"Know Your Role","url":"http:\/\/www.wowprogress.com\/guild\/us\/bronzebeard\/Know+Your+Role\/rating.tier11.ach"},{"score":9808,"world_rank":47976,"area_rank":18356,"realm_rank":68,"name":"Knights of Crate","url":"http:\/\/www.wowprogress.com\/guild\/us\/bronzebeard\/Knights+of+Crate\/rating.tier11.ach"},{"score":9650,"world_rank":48588,"area_rank":18613,"realm_rank":69,"name":"Malicious Mathematics","url":"http:\/\/www.wowprogress.com\/guild\/us\/bronzebeard\/Malicious+Mathematics\/rating.tier11.ach"},{"score":9517,"world_rank":49077,"area_rank":18835,"realm_rank":70,"name":"WaRPeD MiNDs","url":"http:\/\/www.wowprogress.com\/guild\/us\/bronzebeard\/WaRPeD+MiNDs\/rating.tier11.ach"},{"score":9046,"world_rank":50918,"area_rank":19609,"realm_rank":71,"name":"Red Light District","url":"http:\/\/www.wowprogress.com\/guild\/us\/bronzebeard\/Red+Light+District\/rating.tier11.ach"},{"score":9022,"world_rank":51026,"area_rank":19659,"realm_rank":72,"name":"VanDread","url":"http:\/\/www.wowprogress.com\/guild\/us\/bronzebeard\/VanDread\/rating.tier11.ach"},{"score":9000,"world_rank":53303,"area_rank":20528,"realm_rank":73,"name":"The Butcher Shop","url":"http:\/\/www.wowprogress.com\/guild\/us\/bronzebeard\/The+Butcher+Shop\/rating.tier11.ach"},{"score":9000,"world_rank":55035,"area_rank":21208,"realm_rank":74,"name":"Adventure Fun Pals Team","url":"http:\/\/www.wowprogress.com\/guild\/us\/bronzebeard\/Adventure+Fun+Pals+Team\/rating.tier11.ach"},{"score":9000,"world_rank":55355,"area_rank":21331,"realm_rank":75,"name":"Spartan Glory","url":"http:\/\/www.wowprogress.com\/guild\/us\/bronzebeard\/Spartan+Glory\/rating.tier11.ach"},{"score":8995,"world_rank":55895,"area_rank":21565,"realm_rank":76,"name":"Fully Rested","url":"http:\/\/www.wowprogress.com\/guild\/us\/bronzebeard\/Fully+Rested\/rating.tier11.ach"},{"score":8710,"world_rank":56386,"area_rank":21804,"realm_rank":77,"name":"Vexed","url":"http:\/\/www.wowprogress.com\/guild\/us\/bronzebeard\/Vexed\/rating.tier11.ach"},{"score":8610,"world_rank":56535,"area_rank":21870,"realm_rank":78,"name":"The Nightwatch","url":"http:\/\/www.wowprogress.com\/guild\/us\/bronzebeard\/The+Nightwatch\/rating.tier11.ach"},{"score":8470,"world_rank":56753,"area_rank":21966,"realm_rank":79,"name":"Whoville","url":"http:\/\/www.wowprogress.com\/guild\/us\/bronzebeard\/Whoville\/rating.tier11.ach"},{"score":8189,"world_rank":57212,"area_rank":22203,"realm_rank":80,"name":"Clairvoyance","url":"http:\/\/www.wowprogress.com\/guild\/us\/bronzebeard\/Clairvoyance\/rating.tier11.ach"},{"score":8128,"world_rank":57330,"area_rank":22256,"realm_rank":81,"name":"Casus Belli","url":"http:\/\/www.wowprogress.com\/guild\/us\/bronzebeard\/Casus+Belli\/rating.tier11.ach"},{"score":8094,"world_rank":57408,"area_rank":22297,"realm_rank":82,"name":"Devotion","url":"http:\/\/www.wowprogress.com\/guild\/us\/bronzebeard\/Devotion\/rating.tier11.ach"},{"score":7885,"world_rank":57793,"area_rank":22463,"realm_rank":83,"name":"Myth","url":"http:\/\/www.wowprogress.com\/guild\/us\/bronzebeard\/Myth\/rating.tier11.ach"},{"score":7651,"world_rank":58223,"area_rank":22671,"realm_rank":84,"name":"Micro Apocalypse","url":"http:\/\/www.wowprogress.com\/guild\/us\/bronzebeard\/Micro+Apocalypse\/rating.tier11.ach"},{"score":7500,"world_rank":58596,"area_rank":22845,"realm_rank":85,"name":"We Stab You Bleed","url":"http:\/\/www.wowprogress.com\/guild\/us\/bronzebeard\/We+Stab+You+Bleed\/rating.tier11.ach"},{"score":7478,"world_rank":58686,"area_rank":22875,"realm_rank":86,"name":"Shattered Remnants","url":"http:\/\/www.wowprogress.com\/guild\/us\/bronzebeard\/Shattered+Remnants\/rating.tier11.ach"},{"score":7466,"world_rank":58708,"area_rank":22886,"realm_rank":87,"name":"Darkness Raiders","url":"http:\/\/www.wowprogress.com\/guild\/us\/bronzebeard\/Darkness+Raiders\/rating.tier11.ach"},{"score":7322,"world_rank":58983,"area_rank":23018,"realm_rank":88,"name":"Infinit\u00fcs Vox","url":"http:\/\/www.wowprogress.com\/guild\/us\/bronzebeard\/Infinit%C3%BCs+Vox\/rating.tier11.ach"},{"score":7089,"world_rank":59342,"area_rank":23178,"realm_rank":89,"name":"GunZ","url":"http:\/\/www.wowprogress.com\/guild\/us\/bronzebeard\/GunZ\/rating.tier11.ach"},{"score":7000,"world_rank":59918,"area_rank":23429,"realm_rank":90,"name":"Elite Horde Slayers","url":"http:\/\/www.wowprogress.com\/guild\/us\/bronzebeard\/Elite+Horde+Slayers\/rating.tier11.ach"},{"score":6884,"world_rank":60261,"area_rank":23590,"realm_rank":91,"name":"Surreal","url":"http:\/\/www.wowprogress.com\/guild\/us\/bronzebeard\/Surreal\/rating.tier11.ach"},{"score":6717,"world_rank":60531,"area_rank":23705,"realm_rank":92,"name":"Sedia","url":"http:\/\/www.wowprogress.com\/guild\/us\/bronzebeard\/Sedia\/rating.tier11.ach"},{"score":6483,"world_rank":60983,"area_rank":23896,"realm_rank":93,"name":"Conclave of Shadows","url":"http:\/\/www.wowprogress.com\/guild\/us\/bronzebeard\/Conclave+of+Shadows\/rating.tier11.ach"},{"score":5967,"world_rank":62159,"area_rank":24390,"realm_rank":94,"name":"Perfect Symmetry","url":"http:\/\/www.wowprogress.com\/guild\/us\/bronzebeard\/Perfect+Symmetry\/rating.tier11.ach"},{"score":5955,"world_rank":62179,"area_rank":24397,"realm_rank":95,"name":"Does Annulus for Free","url":"http:\/\/www.wowprogress.com\/guild\/us\/bronzebeard\/Does+Annulus+for+Free\/rating.tier11.ach"},{"score":5500,"world_rank":62990,"area_rank":24768,"realm_rank":96,"name":"Affliction","url":"http:\/\/www.wowprogress.com\/guild\/us\/bronzebeard\/Affliction\/rating.tier11.ach"},{"score":5405,"world_rank":63195,"area_rank":24849,"realm_rank":97,"name":"Anomaly","url":"http:\/\/www.wowprogress.com\/guild\/us\/bronzebeard\/Anomaly\/rating.tier11.ach"},{"score":5044,"world_rank":63888,"area_rank":25147,"realm_rank":98,"name":"Daughters of the Horde","url":"http:\/\/www.wowprogress.com\/guild\/us\/bronzebeard\/Daughters+of+the+Horde\/rating.tier11.ach"},{"score":5023,"world_rank":63932,"area_rank":25167,"realm_rank":99,"name":"Last Frontier","url":"http:\/\/www.wowprogress.com\/guild\/us\/bronzebeard\/Last+Frontier\/rating.tier11.ach"},{"score":5000,"world_rank":64219,"area_rank":25264,"realm_rank":100,"name":"Beacons","url":"http:\/\/www.wowprogress.com\/guild\/us\/bronzebeard\/Beacons\/rating.tier11.ach"},{"score":5000,"world_rank":64226,"area_rank":25268,"realm_rank":101,"name":"From Dust","url":"http:\/\/www.wowprogress.com\/guild\/us\/bronzebeard\/From+Dust\/rating.tier11.ach"},{"score":5000,"world_rank":64235,"area_rank":25273,"realm_rank":102,"name":"F T W","url":"http:\/\/www.wowprogress.com\/guild\/us\/bronzebeard\/F+T+W\/rating.tier11.ach"},{"score":4939,"world_rank":64423,"area_rank":25347,"realm_rank":103,"name":"The Legion of Honor","url":"http:\/\/www.wowprogress.com\/guild\/us\/bronzebeard\/The+Legion+of+Honor\/rating.tier11.ach"},{"score":4894,"world_rank":64499,"area_rank":25382,"realm_rank":104,"name":"Relentless","url":"http:\/\/www.wowprogress.com\/guild\/us\/bronzebeard\/Relentless\/rating.tier11.ach"},{"score":4000,"world_rank":66445,"area_rank":26231,"realm_rank":105,"name":"Innuendo","url":"http:\/\/www.wowprogress.com\/guild\/us\/bronzebeard\/Innuendo\/rating.tier11.ach"},{"score":3432,"world_rank":67687,"area_rank":26772,"realm_rank":106,"name":"the Silent Force","url":"http:\/\/www.wowprogress.com\/guild\/us\/bronzebeard\/the+Silent+Force\/rating.tier11.ach"},{"score":3312,"world_rank":67907,"area_rank":26868,"realm_rank":107,"name":"Sons of Redemption","url":"http:\/\/www.wowprogress.com\/guild\/us\/bronzebeard\/Sons+of+Redemption\/rating.tier11.ach"},{"score":3117,"world_rank":68239,"area_rank":27026,"realm_rank":108,"name":"Fat Kids IRL","url":"http:\/\/www.wowprogress.com\/guild\/us\/bronzebeard\/Fat+Kids+IRL\/rating.tier11.ach"},{"score":3000,"world_rank":68442,"area_rank":27112,"realm_rank":109,"name":"Gang of Wolves","url":"http:\/\/www.wowprogress.com\/guild\/us\/bronzebeard\/Gang+of+Wolves\/rating.tier11.ach"},{"score":3000,"world_rank":68463,"area_rank":27123,"realm_rank":110,"name":"Demoted","url":"http:\/\/www.wowprogress.com\/guild\/us\/bronzebeard\/Demoted\/rating.tier11.ach"},{"score":2539,"world_rank":69980,"area_rank":27763,"realm_rank":111,"name":"Southshore Saints","url":"http:\/\/www.wowprogress.com\/guild\/us\/bronzebeard\/Southshore+Saints\/rating.tier11.ach"},{"score":2500,"world_rank":70130,"area_rank":27842,"realm_rank":112,"name":"Virtual Identity","url":"http:\/\/www.wowprogress.com\/guild\/us\/bronzebeard\/Virtual+Identity\/rating.tier11.ach"},{"score":2345,"world_rank":70562,"area_rank":28039,"realm_rank":113,"name":"Momentum","url":"http:\/\/www.wowprogress.com\/guild\/us\/bronzebeard\/Momentum\/rating.tier11.ach"},{"score":2000,"world_rank":71338,"area_rank":28418,"realm_rank":114,"name":"kthxbi","url":"http:\/\/www.wowprogress.com\/guild\/us\/bronzebeard\/kthxbi\/rating.tier11.ach"},{"score":2000,"world_rank":71699,"area_rank":28558,"realm_rank":115,"name":"The Celtic Lords","url":"http:\/\/www.wowprogress.com\/guild\/us\/bronzebeard\/The+Celtic+Lords\/rating.tier11.ach"},{"score":633,"world_rank":75196,"area_rank":30160,"realm_rank":116,"name":"Regicide","url":"http:\/\/www.wowprogress.com\/guild\/us\/bronzebeard\/Regicide\/rating.tier11.ach"},{"score":500,"world_rank":75460,"area_rank":30279,"realm_rank":117,"name":"Ineligible","url":"http:\/\/www.wowprogress.com\/guild\/us\/bronzebeard\/Ineligible\/rating.tier11.ach"}]